MANIFEST.in
README.rst
requirements.txt
setup.py
craftr/__init__.py
craftr/__main__.py
craftr/defaults.py
craftr/foreignbuild.py
craftr/loaders.py
craftr/mods.py
craftr/targetbuilder.py
craftr/core/__init__.py
craftr/core/build.py
craftr/core/config.py
craftr/core/logging.py
craftr/core/manifest.py
craftr/core/renames.py
craftr/core/session.py
craftr/platform/__init__.py
craftr/platform/cygwin.py
craftr/platform/darwin.py
craftr/platform/linux.py
craftr/platform/msys.py
craftr/platform/win32.py
craftr/stl/README.md
craftr/stl/craftr.lang.csharp/Craftrfile
craftr/stl/craftr.lang.csharp/manifest.cson
craftr/stl/craftr.lang.cxx/Craftrfile
craftr/stl/craftr.lang.cxx/README.md
craftr/stl/craftr.lang.cxx/manifest.cson
craftr/stl/craftr.lang.cxx.common/Craftrfile
craftr/stl/craftr.lang.cxx.common/README.md
craftr/stl/craftr.lang.cxx.common/manifest.cson
craftr/stl/craftr.lang.cxx.msvc/Craftrfile
craftr/stl/craftr.lang.cxx.msvc/README.md
craftr/stl/craftr.lang.cxx.msvc/manifest.cson
craftr/stl/craftr.lang.cython/Craftrfile
craftr/stl/craftr.lang.cython/manifest.cson
craftr/stl/craftr.lang.java/Craftrfile
craftr/stl/craftr.lang.java/manifest.cson
craftr/stl/craftr.lang.python/Craftrfile
craftr/stl/craftr.lang.python/manifest.cson
craftr/stl/craftr.lang.thrift/Craftrfile
craftr/stl/craftr.lang.thrift/README.md
craftr/stl/craftr.lang.thrift/manifest.cson
craftr/stl/craftr.lang.vala/Craftrfile
craftr/stl/craftr.lang.vala/manifest.cson
craftr/stl/craftr.utils.archive/Craftrfile
craftr/stl/craftr.utils.archive/README.md
craftr/stl/craftr.utils.archive/manifest.cson
craftr/stl/craftr.utils.cmake/Craftrfile
craftr/stl/craftr.utils.cmake/manifest.cson
craftr/stl/craftr.utils.git/Craftrfile
craftr/stl/craftr.utils.git/manifest.cson
craftr/stl_auxiliary/README.md
craftr/stl_auxiliary/craftr.lib.boost/Craftrfile
craftr/stl_auxiliary/craftr.lib.boost/README.md
craftr/stl_auxiliary/craftr.lib.boost/manifest.json
craftr/stl_auxiliary/craftr.lib.cimg/Craftrfile
craftr_build.egg-info/PKG-INFO
craftr_build.egg-info/SOURCES.txt
craftr_build.egg-info/dependency_links.txt
craftr_build.egg-info/entry_points.txt
craftr_build.egg-info/requires.txt
craftr_build.egg-info/top_level.txt
