Metadata-Version: 1.1
Name: craftr-build
Version: 2.0.0
Summary: Meta build system based on Ninja and Python
Home-page: https://gitlab.niklasrosenstein.com/niklas/craftr
Author: Niklas Rosenstein
Author-email: rosensteinniklas@gmail.com
License: GNU GPL v3
Platform: UNKNOWN
Classifier: Topic :: Software Development
Classifier: Topic :: Software Development :: Build Tools
Classifier: Programming Language :: Python :: 3.4
Classifier: Programming Language :: Python :: 3.5
Classifier: Programming Language :: Python :: 3 :: Only
Classifier: Programming Language :: Python :: Implementation :: CPython
Classifier: License :: OSI Approved :: MIT License
